<annotation>
	<folder>imgdata</folder>
	<filename>KakaoTalk_20210408_134711924_04.jpg</filename>
	<path>C:\Users\HUSTAR13\Desktop\imgdata\KakaoTalk_20210408_134711924_04.jpg</path>
	<source>
		<database>Unknown</database>
	</source>
	<size>
		<width>3024</width>
		<height>4032</height>
		<depth>3</depth>
	</size>
	<segmented>0</segmented>
	<object>
		<name>mark</name>
		<pose>Unspecified</pose>
		<truncated>0</truncated>
		<difficult>0</difficult>
		<bndbox>
			<xmin>658</xmin>
			<ymin>1242</ymin>
			<xmax>2374</xmax>
			<ymax>2946</ymax>
		</bndbox>
	</object>
</annotation>
